README
setup.py
oldowan/__init__.py
oldowan.polymorphism.egg-info/PKG-INFO
oldowan.polymorphism.egg-info/SOURCES.txt
oldowan.polymorphism.egg-info/dependency_links.txt
oldowan.polymorphism.egg-info/namespace_packages.txt
oldowan.polymorphism.egg-info/not-zip-safe
oldowan.polymorphism.egg-info/top_level.txt
oldowan/polymorphism/__init__.py
oldowan/polymorphism/polymorphism.py
oldowan/polymorphism/range.py