Metadata-Version: 1.0
Name: oldowan.polymorphism
Version: 1.0.0
Summary: Utilities for the management of molecular polymorphism data.
